LICENSE
MANIFEST.in
README.md
setup.py
echonetlite/__init__.py
echonetlite/interfaces.py
echonetlite/ipv4adapter.py
echonetlite/middleware.py
echonetlite/protocol.py
echonetlite/shellservice.py
echonetlite.egg-info/PKG-INFO
echonetlite.egg-info/SOURCES.txt
echonetlite.egg-info/dependency_links.txt
echonetlite.egg-info/requires.txt
echonetlite.egg-info/top_level.txt