Metadata-Version: 1.1
Name: echonetlite
Version: 0.0.1
Summary: Echonet Lite
Home-page: https://github.com/keiichishima/echonetlite
Author: Keiichi SHIMA
Author-email: keiichi@iijlab.net
License: BSD License
Platform: UNKNOWN
Classifier: Development Status :: 4 - Beta
Classifier: Environment :: Console
Classifier: Intended Audience :: Developers
Classifier: Intended Audience :: Information Technology
Classifier: License :: OSI Approved :: BSD License
Classifier: Programming Language :: Python :: 3.5
Classifier: Topic :: Home Automation
Classifier: Topic :: System :: Networking
Classifier: Topic :: Software Development :: Libraries :: Python Modules
